reqsync/__init__.py
reqsync/_logging.py
reqsync/_types.py
reqsync/cli.py
reqsync/config.py
reqsync/core.py
reqsync/env.py
reqsync/io.py
reqsync/parse.py
reqsync/policy.py
reqsync/report.py
reqsync-0.1.2.dist-info/METADATA
reqsync-0.1.2.dist-info/WHEEL
reqsync-0.1.2.dist-info/entry_points.txt
reqsync-0.1.2.dist-info/licenses/LICENSE
reqsync-0.1.2.dist-info/RECORD
