Metadata-Version: 2.4
Name: reqsync
Version: 0.1.2
Summary: Synchronize requirements.txt to match installed versions, safely and atomically.
Project-URL: Homepage, https://github.com/ImYourBoyRoy/reqsync
Project-URL: Repository, https://github.com/ImYourBoyRoy/reqsync
Project-URL: Bug Tracker, https://github.com/ImYourBoyRoy/reqsync/issues
Author-email: ImYourBoyRoy <roy.dawson.iv@gmail.com.com>
License: MIT
License-File: LICENSE
Keywords: agent,ai-tool,automation,ci-cd,cli-tool,dependencies,dependency-management,devops,packaging,pip,requirements,venv
Classifier: Development Status :: 4 - Beta
Classifier: Environment :: Console
Classifier: Intended Audience :: Developers
Classifier: Intended Audience :: System Administrators
Classifier: License :: OSI Approved :: MIT License
Classifier: Operating System :: OS Independent
Classifier: Programming Language :: Python :: 3
Classifier: Programming Language :: Python :: 3 :: Only
Classifier: Programming Language :: Python :: 3.8
Classifier: Programming Language :: Python :: 3.9
Classifier: Programming Language :: Python :: 3.10
Classifier: Programming Language :: Python :: 3.11
Classifier: Programming Language :: Python :: 3.12
Classifier: Programming Language :: Python :: 3.13
Classifier: Topic :: Software Development :: Build Tools
Classifier: Topic :: Software Development :: Quality Assurance
Classifier: Topic :: Utilities
Classifier: Typing :: Typed
Requires-Python: >=3.8
Requires-Dist: packaging>=24.1
Requires-Dist: tomli>=2.0; python_version < '3.11'
Requires-Dist: typer>=0.12
Requires-Dist: typing-extensions>=4.7; python_version < '3.11'
Provides-Extra: dev
Requires-Dist: build>=1.2.1; extra == 'dev'
Requires-Dist: mypy>=1.10; extra == 'dev'
Requires-Dist: pytest>=8.2; extra == 'dev'
Requires-Dist: ruff>=0.5.0; extra == 'dev'
Requires-Dist: twine>=5.1; extra == 'dev'
Provides-Extra: pretty
Requires-Dist: rich>=13.7; extra == 'pretty'
